[
  {
    "mcq_id": "br_q01",
    "chapter_id": "c27",
    "question": "Who is the author of the autobiographical excerpt 'Bridges'?",
    "options": ["Anita Desai", "Kumudini Lakhia", "Jhumpa Lahiri", "Padma Sachdev"],
    "correct_index": 1,
    "explanation": "The essay 'Bridges' is written by the famous Kathak dancer and choreographer Kumudini Lakhia.",
    "difficulty": "easy",
    "subject": "English Literature"
  },
  {
    "mcq_id": "br_q02",
    "chapter_id": "c27",
    "question": "According to the author, how would her 'younger self' react to seeing her now?",
    "options": ["Proud", "Incredulous", "Indifferent", "Angry"],
    "correct_index": 1,
    "explanation": "The author starts by saying, 'If my younger self could see me now she would be incredulous.'",
    "difficulty": "medium",
    "subject": "English Literature"
  },
  {
    "mcq_id": "br_q03",
    "chapter_id": "c27",
    "question": "The author finds the claim 'born to dance' made by some dancers to be:",
    "options": ["Inspirational", "Dubious", "Scientific", "Absolutely true"],
    "correct_index": 1,
    "explanation": "She states, 'I find this assertion dubious; it is rarely that easy.'",
    "difficulty": "easy",
    "subject": "English Literature"
  },
  {
    "mcq_id": "br_q04",
    "chapter_id": "c27",
    "question": "As a child, how did the author feel about dancing?",
    "options": ["She loved it from the start", "She never did want to dance", "She was indifferent", "She wanted to be a singer instead"],
    "correct_index": 1,
    "explanation": "The author admits, 'In all truth, as a child, I never did want to dance.'",
    "difficulty": "easy",
    "subject": "English Literature"
  },
  {
    "mcq_id": "br_q05",
    "chapter_id": "c27",
    "question": "Who 'forced' the author to take dance lessons?",
    "options": ["Her school teacher", "Her doting mother", "Her father", "Her grandmother"],
    "correct_index": 1,
    "explanation": "The text says it was forced upon her by a 'doting mother and a silent father.'",
    "difficulty": "easy",
    "subject": "English Literature"
  },
  {
    "mcq_id": "br_q06",
    "chapter_id": "c27",
    "question": "Why did the author's father remain 'silent' regarding her dance lessons?",
    "options": ["He didn't care", "To avoid argument", "He was always at work", "He couldn't speak"],
    "correct_index": 1,
    "explanation": "The author notes, 'My father probably kept his peace to avoid argument.'",
    "difficulty": "medium",
    "subject": "English Literature"
  },
  {
    "mcq_id": "br_q07",
    "chapter_id": "c27",
    "question": "How did the author and her mother travel to the dance class?",
    "options": ["In a private car", "In local, over-crowded trains", "By bus", "Walking"],
    "correct_index": 1,
    "explanation": "The mother travelled in 'local, over-crowded trains to dance class with an unwilling child.'",
    "difficulty": "medium",
    "subject": "English Literature"
  },
  {
    "mcq_id": "br_q08",
    "chapter_id": "c27",
    "question": "Where did the mother wait while the author took her dance lessons?",
    "options": ["In a nearby cafe", "In the not-so-clean ante-room", "In the classroom", "At home"],
    "correct_index": 1,
    "explanation": "She 'waited a whole hour in the not-so-clean ante-room.'",
    "difficulty": "medium",
    "subject": "English Literature"
  },
  {
    "mcq_id": "br_q09",
    "chapter_id": "c27",
    "question": "What does the author compare her life to in the first paragraph?",
    "options": ["A river", "A patchwork", "A straight road", "A book"],
    "correct_index": 1,
    "explanation": "She uses the metaphor: 'as the patchwork of my life comes into clearer focus.'",
    "difficulty": "medium",
    "subject": "English Literature"
  },
  {
    "mcq_id": "br_q10",
    "chapter_id": "c27",
    "question": "What is 'choreography' according to the author's personal comprehension?",
    "options": ["Moving to music", "Deciphering and translating dance", "Exercising", "Watching others dance"],
    "correct_index": 1,
    "explanation": "She defines it as 'decipher and translate dance for my own comprehension, call it choreography if you wish.'",
    "difficulty": "hard",
    "subject": "English Literature"
  },
  {
    "mcq_id": "br_q11",
    "chapter_id": "c27",
    "question": "To dance, according to Kumudini Lakhia, means to ________.",
    "options": ["Fly", "Struggle", "Play", "Sing"],
    "correct_index": 1,
    "explanation": "She states, 'To dance means to struggle.'",
    "difficulty": "easy",
    "subject": "English Literature"
  },
  {
    "mcq_id": "br_q12",
    "chapter_id": "c27",
    "question": "The author believes 'discipline itself is a ________'.",
    "options": ["Gift", "Struggle", "Joy", "Waste"],
    "correct_index": 1,
    "explanation": "She connects dance to discipline, saying 'discipline itself is a struggle.'",
    "difficulty": "medium",
    "subject": "English Literature"
  },
  {
    "mcq_id": "br_q13",
    "chapter_id": "c27",
    "question": "What is the meaning of 'infraction' in the context of the word list?",
    "options": ["A type of dance", "A violation or infringement of a law or agreement", "A mathematical term", "A medical condition"],
    "correct_index": 1,
    "explanation": "Infraction is one of the terms the user is asked to guess the meaning of.",
    "difficulty": "hard",
    "subject": "English Literature"
  },
  {
    "mcq_id": "br_q14",
    "chapter_id": "c27",
    "question": "What is 'demeanour'?",
    "options": ["Outward behavior or bearing", "A type of musical instrument", "A small room", "A dance step"],
    "correct_index": 0,
    "explanation": "Demeanour refers to how a person carries themselves.",
    "difficulty": "medium",
    "subject": "English Literature"
  },
  {
    "mcq_id": "br_q15",
    "chapter_id": "c27",
    "question": "The word 'synergy' refers to:",
    "options": ["Loneliness", "Interaction or cooperation giving a greater combined effect", "Laziness", "A fight"],
    "correct_index": 1,
    "explanation": "Synergy is listed as a term to understand from the context.",
    "difficulty": "medium",
    "subject": "English Literature"
  },
  {
    "mcq_id": "br_q16",
    "chapter_id": "c27",
    "question": "What are the 'bridges' referred to in the title of the essay?",
    "options": ["Physical structures over rivers", "Connections between life experiences and work in dance", "Musical transitions", "Dental tools"],
    "correct_index": 1,
    "explanation": "The author writes about 'clear bridges between my life experiences and my work in dance.'",
    "difficulty": "medium",
    "subject": "English Literature"
  },
  {
    "mcq_id": "br_q17",
    "chapter_id": "c27",
    "question": "The author says she was born to ________.",
    "options": ["Dance", "Live", "Teach", "Rule"],
    "correct_index": 1,
    "explanation": "She notes, 'I believe I was not simply born to dance; I was born to live.'",
    "difficulty": "easy",
    "subject": "English Literature"
  },
  {
    "mcq_id": "br_q18",
    "chapter_id": "c27",
    "question": "How did the author feel when she reached the dance class as a child?",
    "options": ["Energetic", "Unwilling and tired from school", "Excited", "Hungry"],
    "correct_index": 1,
    "explanation": "She was an 'unwilling child, tired from a whole day at school.'",
    "difficulty": "easy",
    "subject": "English Literature"
  },
  {
    "mcq_id": "br_q19",
    "chapter_id": "c27",
    "question": "The 'ante-room' where the mother waited is described as:",
    "options": ["Luxurious", "Not-so-clean", "A garden", "Very cold"],
    "correct_index": 1,
    "explanation": "The mother waited in a 'not-so-clean ante-room.'",
    "difficulty": "medium",
    "subject": "English Literature"
  },
  {
    "mcq_id": "br_q20",
    "chapter_id": "c27",
    "question": "Kumudini Lakhia is a renowned exponent of which dance form?",
    "options": ["Bharatanatyam", "Kathak", "Odissi", "Manipuri"],
    "correct_index": 1,
    "explanation": "She is specifically known as a Kathak dancer and choreographer.",
    "difficulty": "medium",
    "subject": "English Literature"
  },
  {
    "mcq_id": "br_q21",
    "chapter_id": "c27",
    "question": "What is a 'Sonnet' as defined in the literary terms section?",
    "options": ["A 10-line poem", "A lyric poem consisting of fourteen lines", "A three-line Japanese poem", "A long narrative"],
    "correct_index": 1,
    "explanation": "A sonnet is defined as a fourteen-line poem linked by an intricate rhyme scheme.",
    "difficulty": "easy",
    "subject": "English Literature"
  },
  {
    "mcq_id": "br_q22",
    "chapter_id": "c27",
    "question": "A 'Lyric' poem expresses:",
    "options": ["A long historical event", "A state of mind or process of perception, thought, and feeling", "A joke", "A legal code"],
    "correct_index": 1,
    "explanation": "A lyric is a fairly short poem expressing a single speaker's feelings or thoughts.",
    "difficulty": "medium",
    "subject": "English Literature"
  },
  {
    "mcq_id": "br_q23",
    "chapter_id": "c27",
    "question": "What is an 'Ode' according to the text?",
    "options": ["A short funny poem", "A long lyric poem serious in subject and elevated in style", "A dance step", "A musical instrument"],
    "correct_index": 1,
    "explanation": "An ode is a serious, long lyric poem with an elaborate structure.",
    "difficulty": "medium",
    "subject": "English Literature"
  },
  {
    "mcq_id": "br_q24",
    "chapter_id": "c27",
    "question": "The term 'Satire' involves blending a critical attitude with:",
    "options": ["Sadness", "Humour and wit", "Anger", "Silence"],
    "correct_index": 1,
    "explanation": "Satire uses humour to ridicule frailties and follies in human customs.",
    "difficulty": "easy",
    "subject": "English Literature"
  },
  {
    "mcq_id": "br_q25",
    "chapter_id": "c27",
    "question": "A 'Fable' is a brief tale with a ________.",
    "options": ["Song", "Moral", "Map", "Recipe"],
    "correct_index": 1,
    "explanation": "A fable is a short tale, usually with animals, that provides a moral lesson.",
    "difficulty": "easy",
    "subject": "English Literature"
  },
  {
    "mcq_id": "br_q26",
    "chapter_id": "c27",
    "question": "The term 'Dramatic Monologue' usually features:",
    "options": ["A group of people talking", "A single speaker who reveals their own character", "No speaker", "A silent dance"],
    "correct_index": 1,
    "explanation": "In a dramatic monologue, one speaker talks to a silent listener, revealing their character.",
    "difficulty": "medium",
    "subject": "English Literature"
  },
  {
    "mcq_id": "br_q27",
    "chapter_id": "c27",
    "question": "What is 'Allegory'?",
    "options": ["A factual report", "A work in which meaning is represented symbolically", "A type of car", "A short poem"],
    "correct_index": 1,
    "explanation": "An allegory is a story or poem where meanings are conveyed through symbols.",
    "difficulty": "medium",
    "subject": "English Literature"
  },
  {
    "mcq_id": "br_q28",
    "chapter_id": "c27",
    "question": "What is 'Irony'?",
    "options": ["The same as sarcasm", "Actual intent expressed in words that carry the opposite meaning", "A metal", "A long story"],
    "correct_index": 1,
    "explanation": "Irony involves a gap between literal meaning and actual intent.",
    "difficulty": "medium",
    "subject": "English Literature"
  },
  {
    "mcq_id": "br_q29",
    "chapter_id": "c27",
    "question": "The word 'Sarcasm' is described as a:",
    "options": ["Kind word", "Sneering or cutting remark; an ironical taunt", "Gentle laugh", "Scientific term"],
    "correct_index": 1,
    "explanation": "Sarcasm is a harsher form of irony meant to taunt or mock.",
    "difficulty": "medium",
    "subject": "English Literature"
  },
  {
    "mcq_id": "br_q30",
    "chapter_id": "c27",
    "question": "The literary term 'Pathos' refers to portraying an incident to arouse feelings of:",
    "options": ["Happiness", "Pity, tenderness, or sadness", "Fear", "Boredom"],
    "correct_index": 1,
    "explanation": "Pathos targets the reader's emotions of sympathy and sadness.",
    "difficulty": "medium",
    "subject": "English Literature"
  },
  {
    "mcq_id": "br_q31",
    "chapter_id": "c27",
    "question": "A 'Refrain' in poetry is:",
    "options": ["A new poem", "A phrase or sentence repeated at regular intervals", "A title", "The last page"],
    "correct_index": 1,
    "explanation": "A refrain is a repeating element, often at the end of stanzas.",
    "difficulty": "easy",
    "subject": "English Literature"
  },
  {
    "mcq_id": "br_q32",
    "chapter_id": "c27",
    "question": "According to the literary terms, from what did the 'refrain' probably develop?",
    "options": ["The sonnet", "The old ballad", "Scientific essays", "Newspapers"],
    "correct_index": 1,
    "explanation": "The refrain likely originated from traditional ballads.",
    "difficulty": "hard",
    "subject": "English Literature"
  },
  {
    "mcq_id": "br_q33",
    "chapter_id": "c27",
    "question": "The author finds the idea that life and work are 'clearly laid out from the beginning' to be a ________ assertion.",
    "options": ["True", "Dubious", "Helpful", "Common"],
    "correct_index": 1,
    "explanation": "She questions the ease and predetermined nature of such claims.",
    "difficulty": "medium",
    "subject": "English Literature"
  },
  {
    "mcq_id": "br_q34",
    "chapter_id": "c27",
    "question": "In the author's view, why is dance a struggle?",
    "options": ["Because music is hard", "Because discipline itself is a struggle", "Because of her parents", "Because of the trains"],
    "correct_index": 1,
    "explanation": "She links the struggle of dance to the fundamental nature of discipline.",
    "difficulty": "medium",
    "subject": "English Literature"
  },
  {
    "mcq_id": "br_q35",
    "chapter_id": "c27",
    "question": "The author says her life 'comes into clearer focus' like a ________.",
    "options": ["Dream", "Patchwork", "Mirror", "Lens"],
    "correct_index": 1,
    "explanation": "She uses the imagery of various pieces coming together.",
    "difficulty": "easy",
    "subject": "English Literature"
  },
  {
    "mcq_id": "br_q36",
    "chapter_id": "c27",
    "question": "Why does the author feel the conditions were more trying for her mother?",
    "options": ["The mother had to dance", "The mother had to manage an unwilling child and crowded travel", "The mother was sick", "The mother hated music"],
    "correct_index": 1,
    "explanation": "The sacrifice of the parent in enabling the child's training is highlighted.",
    "difficulty": "hard",
    "subject": "English Literature"
  },
  {
    "mcq_id": "br_q37",
    "chapter_id": "c27",
    "question": "What 'peace' did the father keep?",
    "options": ["Silence to avoid argument", "World peace", "Peace in the classroom", "Religious peace"],
    "correct_index": 0,
    "explanation": "The father's silence was a tactic for domestic harmony.",
    "difficulty": "medium",
    "subject": "English Literature"
  },
  {
    "mcq_id": "br_q38",
    "chapter_id": "c27",
    "question": "The author compares her dance work to her 'life ________'.",
    "options": ["Stories", "Experiences", "Money", "Holidays"],
    "correct_index": 1,
    "explanation": "The connection between personal history and professional work is the central theme.",
    "difficulty": "easy",
    "subject": "English Literature"
  },
  {
    "mcq_id": "br_q39",
    "chapter_id": "c27",
    "question": "What is an 'unbelievable' thought for the author's younger self?",
    "options": ["Going to school", "Working in the field of dance", "Travelling by train", "Eating at Foyot's"],
    "correct_index": 1,
    "explanation": "The career path she eventually took was unexpected in her youth.",
    "difficulty": "medium",
    "subject": "English Literature"
  },
  {
    "mcq_id": "br_q40",
    "chapter_id": "c27",
    "question": "What was the mother's state while waiting for the author?",
    "options": ["Reading a book", "Waiting a whole hour in a not-so-clean room", "Sleeping", "Dancing"],
    "correct_index": 1,
    "explanation": "The mother's endurance is emphasized.",
    "difficulty": "medium",
    "subject": "English Literature"
  },
  {
    "mcq_id": "br_q41",
    "chapter_id": "c27",
    "question": "The essay 'Bridges' belongs to which category of prose?",
    "options": ["Scientific report", "Autobiographical excerpt", "Political manifesto", "Short story fiction"],
    "correct_index": 1,
    "explanation": "The 'Essays Introduction' describes 'Bridges' as an autobiographical excerpt.",
    "difficulty": "easy",
    "subject": "English Literature"
  },
  {
    "mcq_id": "br_q42",
    "chapter_id": "c27",
    "question": "Which word is a synonym for 'infraction'?",
    "options": ["Obedience", "Violation", "Health", "Dance"],
    "correct_index": 1,
    "explanation": "An infraction is a breaking of a rule.",
    "difficulty": "medium",
    "subject": "English Literature"
  },
  {
    "mcq_id": "br_q43",
    "chapter_id": "c27",
    "question": "The term 'Patchwork' suggests the author's life was:",
    "options": ["A single piece of cloth", "Made up of many different, varied experiences", "Boring", "Very short"],
    "correct_index": 1,
    "explanation": "It symbolizes complexity and variety.",
    "difficulty": "medium",
    "subject": "English Literature"
  },
  {
    "mcq_id": "br_q44",
    "chapter_id": "c27",
    "question": "The 'trying conditions' were mostly related to:",
    "options": ["The weather", "The effort of travel and the environment of the classes", "The cost of lessons", "The lack of teachers"],
    "correct_index": 1,
    "explanation": "Travel in crowded trains and poor waiting areas are the examples given.",
    "difficulty": "hard",
    "subject": "English Literature"
  },
  {
    "mcq_id": "br_q45",
    "chapter_id": "c27",
    "question": "The author says she 'believes I was born to live' as a counter to being born to ________.",
    "options": ["Work", "Dance", "Cry", "Eat"],
    "correct_index": 1,
    "explanation": "She prioritizes life and broad experience over just a career path.",
    "difficulty": "medium",
    "subject": "English Literature"
  },
  {
    "mcq_id": "br_q46",
    "chapter_id": "c27",
    "question": "Is the listener in a 'Dramatic Monologue' usually allowed to speak?",
    "options": ["Yes", "No", "Always", "They must speak more than the main character"],
    "correct_index": 1,
    "explanation": "The definition says a listener is present who 'does not speak'.",
    "difficulty": "medium",
    "subject": "English Literature"
  },
  {
    "mcq_id": "br_q47",
    "chapter_id": "c27",
    "question": "Which of these is NOT a literary term defined at the end of the text?",
    "options": ["Allegory", "Simile", "Satire", "Pathos"],
    "correct_index": 1,
    "explanation": "While sonnet, ode, and satire are there, simile is not in this specific list.",
    "difficulty": "hard",
    "subject": "English Literature"
  },
  {
    "mcq_id": "br_q48",
    "chapter_id": "c27",
    "question": "What 'compares' the author's younger self to her current self?",
    "options": ["A bridge", "A mirror", "The text itself/incredulity", "A car"],
    "correct_index": 2,
    "explanation": "She looks back with an adult perspective at her childhood resistance.",
    "difficulty": "medium",
    "subject": "English Literature"
  },
  {
    "mcq_id": "br_q49",
    "chapter_id": "c27",
    "question": "The mother is described as 'doting'. This means she is:",
    "options": ["Mean", "Extremely fond and devoted", "Old", "Forgetful"],
    "correct_index": 1,
    "explanation": "Her persistence with the lessons shows her devotion to her child's potential.",
    "difficulty": "medium",
    "subject": "English Literature"
  },
  {
    "mcq_id": "br_q50",
    "chapter_id": "c27",
    "question": "The essay appears in unit ________ of the book.",
    "options": ["5", "6", "7", "8"],
    "correct_index": 2,
    "explanation": "It is Unit 7 of the collection.",
    "difficulty": "hard",
    "subject": "English Literature"
  }
]