[
  {
    "mcq_id": "c4_q01",
    "chapter_id": "c4",
    "question": "What was the only event contested in the first recorded Ancient Olympic Games in 776 B.C.?",
    "options": ["Javelin Throw", "Stadion footrace", "Pentathlon", "Wrestling"],
    "correct_index": 1,
    "explanation": "In 776 B.C., in Olympia, Greece, only one event was contested which was known as the stadion footrace.",
    "ncert_page": 1,
    "difficulty": "medium",
    "subject": "Physical Education"
  },
  {
    "mcq_id": "c4_q02",
    "chapter_id": "c4",
    "question": "Which body is the world governing body for the sport of Athletics?",
    "options": ["IOC", "World Athletics", "IAAF", "AFI"],
    "correct_index": 1,
    "explanation": "World Athletics is the world governing body for the sport of athletics.",
    "ncert_page": 2,
    "difficulty": "easy",
    "subject": "Physical Education"
  },
  {
    "mcq_id": "c4_q03",
    "chapter_id": "c4",
    "question": "The standard length of a running track in a stadium is:",
    "options": ["200m", "400m", "800m", "100m"],
    "correct_index": 1,
    "explanation": "A standard running track is 400 metres in length.",
    "ncert_page": 2,
    "difficulty": "easy",
    "subject": "Physical Education"
  },
  {
    "mcq_id": "c4_q04",
    "chapter_id": "c4",
    "question": "Which of the following is considered a 'Throwing Event' in Athletics?",
    "options": ["Long Jump", "Pole Vault", "Shot Put", "Steeplechase"],
    "correct_index": 2,
    "explanation": "Throwing events include Shot Put, Discus Throw, Hammer Throw, and Javelin Throw.",
    "ncert_page": 2,
    "difficulty": "easy",
    "subject": "Physical Education"
  },
  {
    "mcq_id": "c4_q05",
    "chapter_id": "c4",
    "question": "How many players are there on each side in a standard game of Badminton?",
    "options": ["1 or 2", "3", "4", "5"],
    "correct_index": 0,
    "explanation": "Badminton can be played as 'singles' (one player per side) or 'doubles' (two players per side).",
    "ncert_page": 4,
    "difficulty": "easy",
    "subject": "Physical Education"
  },
  {
    "mcq_id": "c4_q06",
    "chapter_id": "c4",
    "question": "In which country did the modern game of Badminton originate (under the name 'Poona')?",
    "options": ["England", "China", "India", "Malaysia"],
    "correct_index": 2,
    "explanation": "Badminton has its roots in ancient Greece and China, but the modern version 'Poona' originated in India.",
    "ncert_page": 4,
    "difficulty": "medium",
    "subject": "Physical Education"
  },
  {
    "mcq_id": "c4_q07",
    "chapter_id": "c4",
    "question": "Which tournament is considered the 'World Team Championships' for men in Badminton?",
    "options": ["Uber Cup", "Thomas Cup", "Sudirman Cup", "All England"],
    "correct_index": 1,
    "explanation": "The Thomas Cup is the world team championship for men.",
    "ncert_page": 5,
    "difficulty": "medium",
    "subject": "Physical Education"
  },
  {
    "mcq_id": "c4_q08",
    "chapter_id": "c4",
    "question": "A standard Badminton match consists of the best of how many games?",
    "options": ["2", "3", "5", "7"],
    "correct_index": 1,
    "explanation": "A match consists of the best of three games of 21 points.",
    "ncert_page": 6,
    "difficulty": "easy",
    "subject": "Physical Education"
  },
  {
    "mcq_id": "c4_q09",
    "chapter_id": "c4",
    "question": "What is the weight of a standard Badminton shuttlecock?",
    "options": ["4.74 to 5.50 grams", "2.5 to 3.0 grams", "10 to 12 grams", "7 grams"],
    "correct_index": 0,
    "explanation": "The shuttlecock shall weigh from 4.74 to 5.50 grams.",
    "ncert_page": 6,
    "difficulty": "hard",
    "subject": "Physical Education"
  },
  {
    "mcq_id": "c4_q10",
    "chapter_id": "c4",
    "question": "In Gymnastics, what is the term for rhythmic exercises performed without apparatus?",
    "options": ["Artistic Gymnastics", "Calisthenics", "Trampolining", "Vaulting"],
    "correct_index": 1,
    "explanation": "Exercises without apparatus are often called calisthenics.",
    "ncert_page": 8,
    "difficulty": "medium",
    "subject": "Physical Education"
  },
  {
    "mcq_id": "c4_q11",
    "chapter_id": "c4",
    "question": "Which apparatus is used ONLY by male gymnasts in competition?",
    "options": ["Balance Beam", "Uneven Bars", "Pommel Horse", "Floor Exercise"],
    "correct_index": 2,
    "explanation": "The Pommel Horse, Still Rings, Parallel Bars, and High Bar are events specific to men's artistic gymnastics.",
    "ncert_page": 9,
    "difficulty": "medium",
    "subject": "Physical Education"
  },
  {
    "mcq_id": "c4_q12",
    "chapter_id": "c4",
    "question": "Judo was developed in 1882 by which individual?",
    "options": ["Bruce Lee", "Jigoro Kano", "Ichiro Suzuki", "Morihei Ueshiba"],
    "correct_index": 1,
    "explanation": "Judo was created in 1882 by Jigoro Kano as a physical, mental, and moral pedagogy in Japan.",
    "ncert_page": 11,
    "difficulty": "easy",
    "subject": "Physical Education"
  },
  {
    "mcq_id": "c4_q13",
    "chapter_id": "c4",
    "question": "The primary objective in a Judo match is to achieve a score of:",
    "options": ["Waza-ari", "Ippon", "Yuko", "Koka"],
    "correct_index": 1,
    "explanation": "The objective is to score an Ippon (one full point) to win the match instantly.",
    "ncert_page": 12,
    "difficulty": "medium",
    "subject": "Physical Education"
  },
  {
    "mcq_id": "c4_q14",
    "chapter_id": "c4",
    "question": "What is the size of the contest area in a standard Judo mat?",
    "options": ["5m x 5m", "8m x 8m to 10m x 10m", "15m x 15m", "12m x 12m"],
    "correct_index": 1,
    "explanation": "The contest area of the mat is 8m x 8m to 10m x 10m.",
    "ncert_page": 12,
    "difficulty": "hard",
    "subject": "Physical Education"
  },
  {
    "mcq_id": "c4_q15",
    "chapter_id": "c4",
    "question": "In Swimming, which stroke is considered the fastest and is used in 'Freestyle' events?",
    "options": ["Breaststroke", "Backstroke", "Butterfly", "Front Crawl"],
    "correct_index": 3,
    "explanation": "The front crawl is the stroke used in freestyle swimming as it is the fastest.",
    "ncert_page": 15,
    "difficulty": "easy",
    "subject": "Physical Education"
  },
  {
    "mcq_id": "c4_q16",
    "chapter_id": "c4",
    "question": "The length of an Olympic-sized swimming pool is:",
    "options": ["25 metres", "50 metres", "75 metres", "100 metres"],
    "correct_index": 1,
    "explanation": "Standard swimming pools for Olympic games are 50 metres in length.",
    "ncert_page": 16,
    "difficulty": "easy",
    "subject": "Physical Education"
  },
  {
    "mcq_id": "c4_q17",
    "chapter_id": "c4",
    "question": "How many lanes are typically found in a standard Olympic swimming pool?",
    "options": ["6", "8", "10", "12"],
    "correct_index": 1,
    "explanation": "Standard swimming pools have 8 to 10 lanes.",
    "ncert_page": 16,
    "difficulty": "medium",
    "subject": "Physical Education"
  },
  {
    "mcq_id": "c4_q18",
    "chapter_id": "c4",
    "question": "Table Tennis originated in which country during the Victorian era?",
    "options": ["China", "Japan", "England", "Germany"],
    "correct_index": 2,
    "explanation": "The game was invented in England in the early days of the 20th Century.",
    "ncert_page": 18,
    "difficulty": "easy",
    "subject": "Physical Education"
  },
  {
    "mcq_id": "c4_q19",
    "chapter_id": "c4",
    "question": "What is the standard diameter of a Table Tennis ball?",
    "options": ["38 mm", "40 mm", "42 mm", "45 mm"],
    "correct_index": 1,
    "explanation": "The ball is spherical with a diameter of 40 mm.",
    "ncert_page": 19,
    "difficulty": "medium",
    "subject": "Physical Education"
  },
  {
    "mcq_id": "c4_q20",
    "chapter_id": "c4",
    "question": "In Table Tennis, a player wins a game by being the first to reach how many points?",
    "options": ["11", "15", "21", "25"],
    "correct_index": 0,
    "explanation": "A game is won by the first player to score 11 points (unless both score 10).",
    "ncert_page": 20,
    "difficulty": "easy",
    "subject": "Physical Education"
  },
  {
    "mcq_id": "c4_q21",
    "chapter_id": "c4",
    "question": "Which style of Wrestling prohibits the use of legs and attacks below the waist?",
    "options": ["Freestyle", "Greco-Roman", "Judoka", "Sumo"],
    "correct_index": 1,
    "explanation": "In Greco-Roman wrestling, the wrestlers are forbidden to use their legs or to trip their opponents, or to use legs for any action.",
    "ncert_page": 22,
    "difficulty": "medium",
    "subject": "Physical Education"
  },
  {
    "mcq_id": "c4_q22",
    "chapter_id": "c4",
    "question": "Who was the first Indian wrestler to win an Olympic medal (Helsinki 1952)?",
    "options": ["Sushil Kumar", "K.D. Jadhav", "Yogeshwar Dutt", "Sakshi Malik"],
    "correct_index": 1,
    "explanation": "K.D. Jadhav was the first Indian wrestler to win an Olympic medal (Bronze) in 1952.",
    "ncert_page": 22,
    "difficulty": "medium",
    "subject": "Physical Education"
  },
  {
    "mcq_id": "c4_q23",
    "chapter_id": "c4",
    "question": "The octagonal or circular wrestling mat includes a 'danger zone' of which color?",
    "options": ["Blue", "Yellow", "Red", "Green"],
    "correct_index": 2,
    "explanation": "The mat has a red zone (passivity zone) which is 1 metre wide.",
    "ncert_page": 23,
    "difficulty": "medium",
    "subject": "Physical Education"
  },
  {
    "mcq_id": "c4_q24",
    "chapter_id": "c4",
    "question": "Which athlete is known as the 'Payyoli Express'?",
    "options": ["Milkha Singh", "P.T. Usha", "Neeraj Chopra", "Hima Das"],
    "correct_index": 1,
    "explanation": "P.T. Usha is a famous Indian athlete often called the 'Payyoli Express'.",
    "ncert_page": 2,
    "difficulty": "easy",
    "subject": "Physical Education"
  },
  {
    "mcq_id": "c4_q25",
    "chapter_id": "c4",
    "question": "In Badminton, if the score becomes 20-all, a side must lead by how many points to win?",
    "options": ["1", "2", "3", "5"],
    "correct_index": 1,
    "explanation": "If the score becomes 20-all, the side which gains a two-point lead first wins that game.",
    "ncert_page": 6,
    "difficulty": "medium",
    "subject": "Physical Education"
  },
  {
    "mcq_id": "c4_q26",
    "chapter_id": "c4",
    "question": "Which gymnastics event requires a raised wooden beam of 5 metres length and 10 cm width?",
    "options": ["Parallel Bars", "Balance Beam", "Vaulting Horse", "Uneven Bars"],
    "correct_index": 1,
    "explanation": "The Balance Beam is 5 metres long and 10 centimetres wide.",
    "ncert_page": 9,
    "difficulty": "easy",
    "subject": "Physical Education"
  },
  {
    "mcq_id": "c4_q27",
    "chapter_id": "c4",
    "question": "Which Judo term is used by the referee to stop the match temporarily?",
    "options": ["Hajime", "Mate", "Ippon", "Sore-made"],
    "correct_index": 1,
    "explanation": "Mate is the command to wait/stop the action.",
    "ncert_page": 13,
    "difficulty": "medium",
    "subject": "Physical Education"
  },
  {
    "mcq_id": "c4_q28",
    "chapter_id": "c4",
    "question": "Which swimming stroke is the only one where swimmers start in the water?",
    "options": ["Freestyle", "Backstroke", "Breaststroke", "Butterfly"],
    "correct_index": 1,
    "explanation": "Swimmers start in the water for the backstroke event.",
    "ncert_page": 15,
    "difficulty": "easy",
    "subject": "Physical Education"
  },
  {
    "mcq_id": "c4_q29",
    "chapter_id": "c4",
    "question": "What is the height of a Table Tennis net above the table surface?",
    "options": ["10 cm", "15.25 cm", "20 cm", "25 cm"],
    "correct_index": 1,
    "explanation": "The top of the net shall be 15.25 cm above the playing surface.",
    "ncert_page": 19,
    "difficulty": "hard",
    "subject": "Physical Education"
  },
  {
    "mcq_id": "c4_q30",
    "chapter_id": "c4",
    "question": "Which Indian wrestler is the first woman to win an Olympic medal (Rio 2016)?",
    "options": ["Geeta Phogat", "Babita Kumari", "Sakshi Malik", "Vinesh Phogat"],
    "correct_index": 2,
    "explanation": "Sakshi Malik became the first Indian woman wrestler to win an Olympic medal in 2016.",
    "ncert_page": 22,
    "difficulty": "medium",
    "subject": "Physical Education"
  },
  {
    "mcq_id": "c4_q31",
    "chapter_id": "c4",
    "question": "The 'Combined Events' in Athletics for men and women are respectively:",
    "options": ["Heptathlon and Decathlon", "Decathlon and Heptathlon", "Pentathlon and Triathalon", "Marathon and Relay"],
    "correct_index": 1,
    "explanation": "Combined events consist of the decathlon for men and the heptathlon for women.",
    "ncert_page": 2,
    "difficulty": "medium",
    "subject": "Physical Education"
  },
  {
    "mcq_id": "c4_q32",
    "chapter_id": "c4",
    "question": "In Badminton, the height of the net at the center of the court should be:",
    "options": ["1.50 metres", "1.524 metres", "1.55 metres", "1.60 metres"],
    "correct_index": 1,
    "explanation": "The height of the net is 1.524 metres at the center.",
    "ncert_page": 6,
    "difficulty": "hard",
    "subject": "Physical Education"
  },
  {
    "mcq_id": "c4_q33",
    "chapter_id": "c4",
    "question": "A gymnastics routine is judged based on which two scores?",
    "options": ["Speed and Height", "Difficulty and Execution", "Weight and Balance", "Strength and Stamina"],
    "correct_index": 1,
    "explanation": "Gymnastics is scored on Difficulty (D-score) and Execution (E-score).",
    "ncert_page": 9,
    "difficulty": "medium",
    "subject": "Physical Education"
  },
  {
    "mcq_id": "c4_q34",
    "chapter_id": "c4",
    "question": "What color is the Judo uniform (Judogi) worn by the first contestant called for a match?",
    "options": ["White", "Blue", "Black", "Red"],
    "correct_index": 0,
    "explanation": "One contestant wears a white Judogi and the other wears a blue Judogi.",
    "ncert_page": 12,
    "difficulty": "easy",
    "subject": "Physical Education"
  },
  {
    "mcq_id": "c4_q35",
    "chapter_id": "c4",
    "question": "Which of the following is NOT a competitive swimming stroke?",
    "options": ["Breaststroke", "Sidestroke", "Butterfly", "Backstroke"],
    "correct_index": 1,
    "explanation": "Competitive strokes are Freestyle, Backstroke, Breaststroke, and Butterfly.",
    "ncert_page": 15,
    "difficulty": "easy",
    "subject": "Physical Education"
  },
  {
    "mcq_id": "c4_q36",
    "chapter_id": "c4",
    "question": "The Table Tennis table is how long and how wide?",
    "options": ["2.74m long, 1.525m wide", "3.00m long, 2.00m wide", "2.50m long, 1.50m wide", "2.74m long, 1.25m wide"],
    "correct_index": 0,
    "explanation": "The table is 2.74m long and 1.525m wide.",
    "ncert_page": 19,
    "difficulty": "hard",
    "subject": "Physical Education"
  },
  {
    "mcq_id": "c4_q37",
    "chapter_id": "c4",
    "question": "Winning by 'Fall' (pinning the opponent's shoulders to the mat) ends the match in which sport?",
    "options": ["Judo", "Wrestling", "Badminton", "Gymnastics"],
    "correct_index": 1,
    "explanation": "A fall is achieved when both shoulders of a wrestler are pinned to the mat.",
    "ncert_page": 24,
    "difficulty": "easy",
    "subject": "Physical Education"
  },
  {
    "mcq_id": "c4_q38",
    "chapter_id": "c4",
    "question": "In Athletics, what is the weight of the Shot Put for senior men?",
    "options": ["4 kg", "5 kg", "7.26 kg", "8 kg"],
    "correct_index": 2,
    "explanation": "The shot put for men weighs 7.260 kg.",
    "ncert_page": 3,
    "difficulty": "hard",
    "subject": "Physical Education"
  },
  {
    "mcq_id": "c4_q39",
    "chapter_id": "c4",
    "question": "Which Indian female badminton player has won two Olympic medals?",
    "options": ["Saina Nehwal", "P.V. Sindhu", "Jwala Gutta", "Ashwini Ponnappa"],
    "correct_index": 1,
    "explanation": "P.V. Sindhu has won two Olympic medals for India in Badminton.",
    "ncert_page": 5,
    "difficulty": "easy",
    "subject": "Physical Education"
  },
  {
    "mcq_id": "c4_q40",
    "chapter_id": "c4",
    "question": "The 'Vault' event is common to:",
    "options": ["Both Men and Women Gymnasts", "Only Men Gymnasts", "Only Women Gymnasts", "Men and Women swimmers"],
    "correct_index": 0,
    "explanation": "Vaulting is an event for both men and women in artistic gymnastics.",
    "ncert_page": 9,
    "difficulty": "medium",
    "subject": "Physical Education"
  },
  {
    "mcq_id": "c4_q41",
    "chapter_id": "c4",
    "question": "What is the duration of a standard Judo match for seniors?",
    "options": ["3 minutes", "4 minutes", "5 minutes", "10 minutes"],
    "correct_index": 1,
    "explanation": "A match lasts four minutes for seniors.",
    "ncert_page": 13,
    "difficulty": "medium",
    "subject": "Physical Education"
  },
  {
    "mcq_id": "c4_q42",
    "chapter_id": "c4",
    "question": "In Swimming, the 'Individual Medley' event follows which stroke order?",
    "options": ["Butterfly, Backstroke, Breaststroke, Freestyle", "Freestyle, Breaststroke, Backstroke, Butterfly", "Butterfly, Breaststroke, Backstroke, Freestyle", "Backstroke, Butterfly, Breaststroke, Freestyle"],
    "correct_index": 0,
    "explanation": "Individual Medley order is Butterfly, Backstroke, Breaststroke, and Freestyle.",
    "ncert_page": 15,
    "difficulty": "hard",
    "subject": "Physical Education"
  },
  {
    "mcq_id": "c4_q43",
    "chapter_id": "c4",
    "question": "What is the standard height of a Table Tennis table from the ground?",
    "options": ["70 cm", "76 cm", "80 cm", "90 cm"],
    "correct_index": 1,
    "explanation": "The playing surface is in a horizontal plane 76 cm above the floor.",
    "ncert_page": 19,
    "difficulty": "hard",
    "subject": "Physical Education"
  },
  {
    "mcq_id": "c4_q44",
    "chapter_id": "c4",
    "question": "Which Indian wrestler is the only one to win two individual Olympic medals?",
    "options": ["Sushil Kumar", "Yogeshwar Dutt", "Bajrang Punia", "Ravi Dahiya"],
    "correct_index": 0,
    "explanation": "Sushil Kumar is the only Indian wrestler to win two individual Olympic medals.",
    "ncert_page": 22,
    "difficulty": "easy",
    "subject": "Physical Education"
  },
  {
    "mcq_id": "c4_q45",
    "chapter_id": "c4",
    "question": "The Marathon race distance is exactly:",
    "options": ["40 km", "42.195 km", "45 km", "50 km"],
    "correct_index": 1,
    "explanation": "The standard distance for a marathon is 42.195 kilometres.",
    "ncert_page": 2,
    "difficulty": "easy",
    "subject": "Physical Education"
  },
  {
    "mcq_id": "c4_q46",
    "chapter_id": "c4",
    "question": "The Sudirman Cup in Badminton is for:",
    "options": ["Men's team", "Women's team", "Mixed teams", "Individual players only"],
    "correct_index": 2,
    "explanation": "The Sudirman Cup is the world mixed team championship.",
    "ncert_page": 5,
    "difficulty": "medium",
    "subject": "Physical Education"
  },
  {
    "mcq_id": "c4_q47",
    "chapter_id": "c4",
    "question": "Uneven Bars is a gymnastics event for:",
    "options": ["Only Women", "Only Men", "Both Men and Women", "Children only"],
    "correct_index": 0,
    "explanation": "Uneven Bars is an event specific to women's artistic gymnastics.",
    "ncert_page": 9,
    "difficulty": "easy",
    "subject": "Physical Education"
  },
  {
    "mcq_id": "c4_q48",
    "chapter_id": "c4",
    "question": "What is the penalty for a false start in modern athletics?",
    "options": ["Warning", "Disqualification", "5-second penalty", "Restart with 1-meter back"],
    "correct_index": 1,
    "explanation": "Any athlete responsible for a false start shall be disqualified.",
    "ncert_page": 3,
    "difficulty": "medium",
    "subject": "Physical Education"
  },
  {
    "mcq_id": "c4_q49",
    "chapter_id": "c4",
    "question": "In Table Tennis, service changes after every how many points?",
    "options": ["1", "2", "5", "10"],
    "correct_index": 1,
    "explanation": "Service shall change after every 2 points have been scored.",
    "ncert_page": 20,
    "difficulty": "medium",
    "subject": "Physical Education"
  },
  {
    "mcq_id": "c4_q50",
    "chapter_id": "c4",
    "question": "A Judo score that is less than Ippon but still significant is:",
    "options": ["Mate", "Waza-ari", "Judogi", "Tatami"],
    "correct_index": 1,
    "explanation": "Waza-ari is a score awarded in Judo that is lower than Ippon.",
    "ncert_page": 12,
    "difficulty": "medium",
    "subject": "Physical Education"
  }
]