{
  "books": [
    { "id": 1211, "title": "Accountancy Part I", "subtitle": "Class 12 NCERT Textbook", "coverUrl": "https://ncert.nic.in/textbook/pdf/cover/leac1.jpg", "language": "english", "classNumber": "Class 12", "subject": "Accountancy", "chapterCount": 5 },
    { "id": 1212, "title": "Accountancy Part II", "subtitle": "Class 12 NCERT Textbook (Company Accounts)", "coverUrl": "https://ncert.nic.in/textbook/pdf/cover/leac2.jpg", "language": "english", "classNumber": "Class 12", "subject": "Accountancy", "chapterCount": 4 },
    { "id": 1213, "title": "Business Studies Part I", "subtitle": "Class 12 NCERT Textbook", "coverUrl": "https://ncert.nic.in/textbook/pdf/cover/lebs1.jpg", "language": "english", "classNumber": "Class 12", "subject": "Business Studies", "chapterCount": 5 },
    { "id": 1214, "title": "Business Studies Part II", "subtitle": "Class 12 NCERT Textbook", "coverUrl": "https://ncert.nic.in/textbook/pdf/cover/lebs2.jpg", "language": "english", "classNumber": "Class 12", "subject": "Business Studies", "chapterCount": 7 },
    { "id": 1215, "title": "Introductory Macroeconomics", "subtitle": "Class 12 NCERT Textbook", "coverUrl": "https://ncert.nic.in/textbook/pdf/cover/leco1.jpg", "language": "english", "classNumber": "Class 12", "subject": "Economics", "chapterCount": 6 },
    { "id": 1216, "title": "Indian Economic Development", "subtitle": "Class 12 NCERT Textbook", "coverUrl": "https://ncert.nic.in/textbook/pdf/cover/leco2.jpg", "language": "english", "classNumber": "Class 12", "subject": "Economics", "chapterCount": 10 }
  ]
}
