[
  {
    "book_id": "class6_science_en",
    "title": "Science",
    "class_id": 6,
    "subject": "Science",
    "medium": "English",
    "cover_url": "https://raw.githubusercontent.com/pramodhshinde/ncert-data/main/covers/class6_science.png",
    "chapter_count": 16,
    "total_pages": 198,
    "size_mb": 18.4,
    "rating": 4.5,
    "chapters_url": "https://raw.githubusercontent.com/pramodhshinde/ncert-data/refs/heads/main/data/class_6/science/chapters.json"
  },
  {
    "book_id": "class6_math_en",
    "title": "Mathematics",
    "class_id": 6,
    "subject": "Mathematics",
    "medium": "English",
    "cover_url": "https://raw.githubusercontent.com/pramodhshinde/ncert-data/main/covers/class6_math.png",
    "chapter_count": 14,
    "total_pages": 308,
    "size_mb": 22.1,
    "rating": 4.3,
    "chapters_url": "https://raw.githubusercontent.com/pramodhshinde/ncert-data/refs/heads/main/data/class_6/science/chapters.json"
  },
  {
    "book_id": "class6_english_en",
    "title": "Honeysuckle (English)",
    "class_id": 6,
    "subject": "English",
    "medium": "English",
    "cover_url": "https://raw.githubusercontent.com/pramodhshinde/ncert-data/main/covers/class6_english.png",
    "chapter_count": 10,
    "total_pages": 146,
    "size_mb": 12.7,
    "rating": 4.1,
    "chapters_url": "https://raw.githubusercontent.com/pramodhshinde/ncert-data/main/data/class_6/english/chapters.json"
  },
  {
    "book_id": "class6_hindi_hi",
    "title": "Vasant (Hindi)",
    "class_id": 6,
    "subject": "Hindi",
    "medium": "Hindi",
    "cover_url": "https://raw.githubusercontent.com/pramodhshinde/ncert-data/main/covers/class6_hindi.png",
    "chapter_count": 17,
    "total_pages": 162,
    "size_mb": 14.3,
    "rating": 4.0,
    "chapters_url": "https://raw.githubusercontent.com/pramodhshinde/ncert-data/main/data/class_6/hindi/chapters.json"
  },
  {
    "book_id": "class6_history_en",
    "title": "Our Pasts I (History)",
    "class_id": 6,
    "subject": "History",
    "medium": "English",
    "cover_url": "https://raw.githubusercontent.com/pramodhshinde/ncert-data/main/covers/class6_history.png",
    "chapter_count": 12,
    "total_pages": 156,
    "size_mb": 15.6,
    "rating": 4.2,
    "chapters_url": "https://raw.githubusercontent.com/pramodhshinde/ncert-data/main/data/class_6/history/chapters.json"
  },
  {
    "book_id": "class6_geography_en",
    "title": "The Earth Our Habitat (Geography)",
    "class_id": 6,
    "subject": "Geography",
    "medium": "English",
    "cover_url": "https://raw.githubusercontent.com/pramodhshinde/ncert-data/main/covers/class6_geography.png",
    "chapter_count": 8,
    "total_pages": 100,
    "size_mb": 11.2,
    "rating": 4.1,
    "chapters_url": "https://raw.githubusercontent.com/pramodhshinde/ncert-data/main/data/class_6/geography/chapters.json"
  }
]
